crypt_tool/__init__.py
crypt_tool/binary_converter.py
crypt_tool/cipher.py
crypt_tool/rng.py
crypt_tool-0.1.2.dist-info/METADATA
crypt_tool-0.1.2.dist-info/WHEEL
crypt_tool-0.1.2.dist-info/top_level.txt
crypt_tool-0.1.2.dist-info/RECORD
