Metadata-Version: 2.1
Name: crypt_tool
Version: 0.1.2
Summary: A versatile and efficient cryptography library implemented in Python
Author-email: Guo Fei <me@guofei.site>
License: MIT
Project-URL: homepage, https://github.com/guofei9987/CryptTool
Project-URL: repository, https://github.com/guofei9987/CryptTool
Requires-Python: >=3.6
